gestured_meeting/__init__.py
gestured_meeting/arg.py
gestured_meeting/event.py
gestured_meeting/gesture/__init__.py
gestured_meeting/gesture/base.py
gestured_meeting/gesture/ble.py
gestured_meeting/icons/default.png
gestured_meeting/icons/icon.svg
gestured_meeting/icons/loading.png
gestured_meeting/meeting/__init__.py
gestured_meeting/meeting/base.py
gestured_meeting/meeting/meet.py
gestured_meeting/meeting/zoom.py
gestured_meeting/ui.py
gestured_meeting-0.1.7.dist-info/entry_points.txt
gestured_meeting-0.1.7.dist-info/WHEEL
gestured_meeting-0.1.7.dist-info/METADATA
gestured_meeting-0.1.7.dist-info/RECORD
