Metadata-Version: 2.1
Name: gestured-meeting
Version: 0.1.7
Summary: Online meeting with gesture.
License: MIT
Author: ygkn
Author-email: 2000ygkn0713@gmail.com
Requires-Python: >=3.9,<4.0
Classifier: License :: OSI Approved :: MIT License
Classifier: Programming Language :: Python :: 3
Classifier: Programming Language :: Python :: 3.10
Classifier: Programming Language :: Python :: 3.9
Requires-Dist: Pillow (>=8.3.2,<9.0.0)
Requires-Dist: PyAutoGUI (>=0.9.53,<0.10.0)
Requires-Dist: PyGObject (>=3.42.0,<4.0.0); platform_system == "Linux"
Requires-Dist: bleak (>=0.12.1,<0.13.0)
Requires-Dist: pystray (>=0.17.3,<0.18.0)
